emi.py
emi_calculator-1.1.dist-info/LICENSE
emi_calculator-1.1.dist-info/METADATA
emi_calculator-1.1.dist-info/WHEEL
emi_calculator-1.1.dist-info/top_level.txt
emi_calculator-1.1.dist-info/RECORD
