Metadata-Version: 2.1
Name: emi-calculator
Version: 1.1
Summary: The EMI Library is a Python library that provides a convenient way to calculate the Equated Monthly Installment (EMI) for loans. The library implements the EMI formula, which takes into account the principal loan amount, interest rate, and tenure in months.
Author-email: Lalit Rajbanshi <lalitrajbanshi45@gmail.com>
Project-URL: Homepage, https://github.com/zack1o1/emi-calculator
Classifier: Programming Language :: Python :: 3
Classifier: License :: OSI Approved :: MIT License
Classifier: Operating System :: OS Independent
Requires-Python: >=3.7
License-File: LICENSE
